{"id":"53e09999232050bb6b53ce33","idMemberCreator":"53d097f91cb25024461e3efd","data":{"board":{"shortLink":"0GuDZG62","name":"Cape Town - Kanban","id":"53d0c20db03b0a44cfcca509"},"card":{"shortLink":"4LGRDh3m","idShort":71,"name":"CW - Report For the year to date, Per day, A Count of all verified judgments","id":"53db53a3a37fa5e8d4ae22fb"},"text":"Still waiting feedback from Neil if I can move this task.@jakovanrensburg"},"type":"commentCard","date":"2014-08-05T08:45:13.931Z","memberCreator":{"id":"53d097f91cb25024461e3efd","avatarHash":null,"fullName":"Gillian Oberholzer","initials":"GO","username":"gillianoberholzer"}}