{"id":"56138fbf76a6b028dc5d6269","idMemberCreator":"53d097f91cb25024461e3efd","data":{"list":{"name":"In Testing (Max 10)","id":"53d0c20db03b0a44cfcca50d"},"board":{"shortLink":"nkiN4mz2","name":"Cape Town - 2015","id":"54855ffbe150073e233562be"},"card":{"shortLink":"OBvBwRPM","idShort":635,"name":"CW - GCCW187 - Assign Case","id":"561370947748bfcdb3deb57d"},"text":"To Neil\n@lylenutt "},"type":"commentCard","date":"2015-10-06T09:09:19.135Z","memberCreator":{"id":"53d097f91cb25024461e3efd","avatarHash":null,"fullName":"Gillian Oberholzer","initials":"GO","username":"gillianoberholzer"}}