{"id":"54b781d4dc6c1583a4bcb83a","idMemberCreator":"53d097f91cb25024461e3efd","data":{"listAfter":{"name":"Ready To Release","id":"53d0c20db03b0a44cfcca50e"},"listBefore":{"name":"In Testing (Max 10)","id":"53d0c20db03b0a44cfcca50d"},"board":{"shortLink":"nkiN4mz2","name":"Cape Town - 2015","id":"54855ffbe150073e233562be"},"card":{"shortLink":"flTepQPz","idShort":113,"name":"CC - Activation Emails to sales person","id":"5491415e72499552c7fddc0d","idList":"53d0c20db03b0a44cfcca50e"},"old":{"idList":"53d0c20db03b0a44cfcca50d"}},"type":"updateCard","date":"2015-01-15T09:01:08.683Z","memberCreator":{"id":"53d097f91cb25024461e3efd","avatarHash":null,"fullName":"Gillian Oberholzer","initials":"GO","username":"gillianoberholzer"}}