{"id":"541946f433426d8bdeee93bd","idMemberCreator":"53d097f91cb25024461e3efd","data":{"list":{"name":"Gathering Information","id":"53db2201d11c89ed43fc5a6a"},"board":{"shortLink":"0GuDZG62","name":"Cape Town - Kanban","id":"53d0c20db03b0a44cfcca509"},"card":{"shortLink":"x0vWFLLX","idShort":204,"name":"CW - Client log in issue","id":"5416ed4fc20073df65565987"},"text":"Issue sorted. @jakovanrensburg"},"type":"commentCard","date":"2014-09-17T08:31:48.902Z","memberCreator":{"id":"53d097f91cb25024461e3efd","avatarHash":null,"fullName":"Gillian Oberholzer","initials":"GO","username":"gillianoberholzer"}}