{"id":"54dc64d09870bda96b353f02","idMemberCreator":"53d0b2dfdbb677b722c39443","data":{"list":{"name":"In Progress (Max 9)","id":"548561eb7a11dac78511a729"},"board":{"name":"Investigation","id":"5524c266ecb4ced4cdb44411"},"card":{"shortLink":"e0O8KnGK","idShort":183,"name":"SW - Owners in Scheme not found","id":"54d8be0816571f8e8e3dedfc"},"text":"@shaunviljoen @gillianoberholzer @stefanbar \nHi - SS Summer View is a scheme registered in 2014.\n\nIt is very plausible that it might not be on LS records yet.\nSo - this is not a fault on our part. Maybe we can, just for completeness sake, check with LS to see if they have it?\n\nMoving ticket to waiting more info"},"type":"commentCard","date":"2015-02-12T08:31:12.748Z","memberCreator":{"id":"53d0b2dfdbb677b722c39443","avatarHash":null,"fullName":"Willem Human","initials":"WH","username":"willemhuman"}}