{"id":"555b0cefbbff45bf4321e399","idMemberCreator":"53cfc3dbf80a9a2e4631c72c","data":{"list":{"name":"Pending Tasks","id":"548561db38fd879b2bc329e5"},"board":{"name":"Investigation","id":"5524c266ecb4ced4cdb44411"},"card":{"shortLink":"CEbk26IR","idShort":327,"name":"CW - Rescission not sent to bureaus","id":"5555bb0f3ddc6a186eeca0ab"},"text":"@gillianoberholzer \n\nIs that image from the Attorney System?\nThe record was Verified in the new CourtWorks system on \"2014-08-20 10:36:31.363\" but not extracted to Bureaus as there is no ID Number added.\n\nThe Admin can amend the case and it should go out tomorrow.\nAny record amended by Admin will be sent out the next day again."},"type":"commentCard","date":"2015-05-19T10:14:07.068Z","memberCreator":{"id":"53cfc3dbf80a9a2e4631c72c","avatarHash":null,"fullName":"Yasser Ogier","initials":"YO","username":"yasserogier"}}