{"id":"550012018b03d065f110bc25","idMemberCreator":"53d097f91cb25024461e3efd","data":{"list":{"name":"In Progress (Max 9)","id":"548561eb7a11dac78511a729"},"board":{"shortLink":"nkiN4mz2","name":"Cape Town - 2015","id":"54855ffbe150073e233562be"},"card":{"shortLink":"EMrHD5Qa","idShort":247,"name":"SW - Bridging deals to be deleted","id":"54fffdf35726f1e828f69e01"},"text":"@yasserogier @lylenutt Sorry, Chantelle provided incorrect data. See attached and ignore the last four sent previously. Yes delete entire matter."},"type":"commentCard","date":"2015-03-11T09:59:29.480Z","memberCreator":{"id":"53d097f91cb25024461e3efd","avatarHash":null,"fullName":"Gillian Oberholzer","initials":"GO","username":"gillianoberholzer"}}