{"id":"55c1e646c6fdbdb8175b9481","idMemberCreator":"53d0b2dfdbb677b722c39443","data":{"list":{"name":"In Progress (Max 9)","id":"548561eb7a11dac78511a729"},"board":{"shortLink":"nkiN4mz2","name":"Cape Town - 2015","id":"54855ffbe150073e233562be"},"card":{"shortLink":"P5ovD2nz","idShort":508,"name":"CW - GCCW159 - Fast capture issues","id":"55c1cd1c7c44ba1f32fa8e31"},"text":"@neilbosworth @lungisaximbi @lylenutt \n\nThe on hold issue sorted on Live"},"type":"commentCard","date":"2015-08-05T10:32:38.641Z","memberCreator":{"id":"53d0b2dfdbb677b722c39443","avatarHash":null,"fullName":"Willem Human","initials":"WH","username":"willemhuman"}}