{"id":"54c78d94bc4a7f8eddb6947a","idMemberCreator":"53d0b2dfdbb677b722c39443","data":{"list":{"name":"In Testing (Max 10)","id":"53d0c20db03b0a44cfcca50d"},"board":{"shortLink":"nkiN4mz2","name":"Cape Town - 2015","id":"54855ffbe150073e233562be"},"card":{"shortLink":"JRlOpYbH","idShort":151,"name":"CW - CCW265 - Date format","id":"54c77c989b530577a80b829e"},"text":"@gillianoberholzer @yasserogier @neilbosworth \nThe issue derived from my work I did yesterday to fix the 6 month old issue to include admin orders again.\nI had to change regional settings on my PC to test, but did not notice the config setting that Visual Studio automatically added."},"type":"commentCard","date":"2015-01-27T13:07:32.442Z","memberCreator":{"id":"53d0b2dfdbb677b722c39443","avatarHash":null,"fullName":"Willem Human","initials":"WH","username":"willemhuman"}}