{"id":"55f906bc5a0c439a299f1774","idMemberCreator":"53d0f06e86ebecc388380ce0","data":{"list":{"name":"Pending Tasks","id":"548561db38fd879b2bc329e5"},"board":{"shortLink":"nkiN4mz2","name":"Cape Town - 2015","id":"54855ffbe150073e233562be"},"card":{"shortLink":"qHIeW74w","idShort":597,"name":"CW - GCCW180 - Judgments verification report","id":"55f7ba36a1c331d229b6610c"},"text":"@neilbosworth \n\n1. That I\u0027m not sure of, I\u0027ll have to look into that.\n\n2. I haven\u0027t made any changes.\n\n3. Have you got a spec for the reports that were created and were any      changes requested that might have gone live?\n\n@gillianoberholzer @yasserogier "},"type":"commentCard","date":"2015-09-16T06:05:48.392Z","memberCreator":{"id":"53d0f06e86ebecc388380ce0","avatarHash":"","fullName":"Lyle Nutt","initials":"LN","username":"lylenutt"}}