{"id":"54ec3e5d59aa4c80b04dccb9","idMemberCreator":"53d0f06e86ebecc388380ce0","data":{"list":{"name":"On Hold (Awaiting Dev Slot)","id":"548561e4e733e8c296c8f476"},"board":{"shortLink":"nkiN4mz2","name":"Cape Town - 2015","id":"54855ffbe150073e233562be"},"card":{"shortLink":"rBdWl7Nk","idShort":209,"name":"CW - CCW290 - Add columns to reports","id":"54e5bea8cda2c44a431a5f0a"},"text":"This is done. but links in with CW - CCW288 - Assign agent enhancement."},"type":"commentCard","date":"2015-02-24T09:03:25.876Z","memberCreator":{"id":"53d0f06e86ebecc388380ce0","avatarHash":"","fullName":"Lyle Nutt","initials":"LN","username":"lylenutt"}}