{"id":"53db29c3db99154f8815a845","idMemberCreator":"53db26ef44764d14b1c49249","data":{"board":{"name":"Cape Town - 2015","id":"54855ffbe150073e233562be"},"card":{"shortLink":"97xRDQXL","idShort":63,"name":"SW - Bridging Finance for foreign nationals","id":"53d8f4411491b05dbfd79d20"},"text":"I presume this issue was resolved prior to release as i see no comments?"},"type":"commentCard","date":"2014-08-01T05:46:43.073Z","memberCreator":{"id":"53db26ef44764d14b1c49249","avatarHash":"2f66ac51e8ff606990044d4c58638506","fullName":"Shaun Viljoen","initials":"SV","username":"shaunviljoen"}}