{"id":"54056a8931f1c231a87cf254","idMemberCreator":"53d0f06e86ebecc388380ce0","data":{"list":{"name":"On Hold (Awaiting Dev Slot)","id":"53edcd89086fdfe0ccd4712c"},"board":{"name":"Cape Town - 2015","id":"54855ffbe150073e233562be"},"card":{"shortLink":"CMN2d0ZS","idShort":158,"name":"SW - Just Group White Label","id":"540551d3ba40506077e52e8c"},"text":"@stefanbar changes taken up"},"type":"commentCard","date":"2014-09-02T06:58:17.682Z","memberCreator":{"id":"53d0f06e86ebecc388380ce0","avatarHash":"","fullName":"Lyle Nutt","initials":"LN","username":"lylenutt"}}