{"id":"53f301425e7ca63e02b23b38","idMemberCreator":"53d0f06e86ebecc388380ce0","data":{"board":{"shortLink":"0GuDZG62","name":"Cape Town - Kanban","id":"53d0c20db03b0a44cfcca509"},"card":{"shortLink":"QdAj5sQd","idShort":118,"name":"VW - Client Management Enhancements","id":"53edc3bab083e0d53a694ec8"},"text":"@cobuspienaar let me know when you ready to start with this so that I can email you the sprocs"},"type":"commentCard","date":"2014-08-19T07:48:18.401Z","memberCreator":{"id":"53d0f06e86ebecc388380ce0","avatarHash":"","fullName":"Lyle Nutt","initials":"LN","username":"lylenutt"}}