{"id":"546b0119a0982b5b0421631c","checkItemStates":[],"closed":true,"dateLastActivity":"2015-01-09T06:14:28.049Z","desc":"","descData":null,"idBoard":"54855ffbe150073e233562be","idList":"53d0c20db03b0a44cfcca50d","idMembersVoted":[],"idShort":101,"idAttachmentCover":null,"manualCoverAttachment":false,"idLabels":["54855ffb74d650d567b90183"],"name":"SW - API, Add integration support","pos":896,"shortLink":"q33OzdSV","badges":{"votes":0,"viewingMemberVoted":false,"subscribed":false,"fogbugz":"","checkItems":0,"checkItemsChecked":0,"comments":2,"attachments":0,"description":false,"due":null},"due":null,"email":"jakovanrensburg+53cfbb55f833a01546975bd3+546b0119a0982b5b0421631c+c3510489a75a688e6f66b8ae58904057847909f4@boards.trello.com","idChecklists":[],"idMembers":[],"labels":[{"id":"54855ffb74d650d567b90183","idBoard":"54855ffbe150073e233562be","name":"Enhancement","color":"green","uses":139}],"shortUrl":"https://trello.com/c/q33OzdSV","subscribed":false,"url":"https://trello.com/c/q33OzdSV/101-sw-api-add-integration-support"}