{"id":"53edcf124842f406b7fae515","idMemberCreator":"53cfbb55f833a01546975bd3","data":{"board":{"name":"Cape Town - 2015","id":"54855ffbe150073e233562be"},"card":{"shortLink":"kRcnmfDM","idShort":95,"name":"Deed Quote Generator","id":"53e87aafef067e4d70ed9f7f"},"text":"@gillianoberholzer any news here yet?"},"type":"commentCard","date":"2014-08-15T09:12:50.503Z","memberCreator":{"id":"53cfbb55f833a01546975bd3","avatarHash":"f303f406818d7519d91c3c089e1c27a8","fullName":"Jako van Rensburg","initials":"JR","username":"jakovanrensburg"}}