{"id":"54b4b70b5c1f13d2f391f188","idMemberCreator":"53cfc3dbf80a9a2e4631c72c","data":{"listAfter":{"name":"Awaiting Support / More Info","id":"548561d74df012abdef092c7"},"listBefore":{"name":"In Progress (Max 9)","id":"548561eb7a11dac78511a729"},"board":{"shortLink":"nkiN4mz2","name":"Cape Town - 2015","id":"54855ffbe150073e233562be"},"card":{"shortLink":"Yl2dj259","idShort":118,"name":"CW - ANTCCW045 - Nedbank data extract","id":"54af7ba0664e8e5d43620910","idList":"548561d74df012abdef092c7"},"old":{"idList":"548561eb7a11dac78511a729"}},"type":"updateCard","date":"2015-01-13T06:11:23.762Z","memberCreator":{"id":"53cfc3dbf80a9a2e4631c72c","avatarHash":null,"fullName":"Yasser Ogier","initials":"YO","username":"yasserogier"}}