{"id":"5440c8eca7a70ca9c943bb22","idMemberCreator":"53d2098c5dc4ef2c4b37773d","data":{"dateLastEdited":"2014-10-17T07:44:55.059Z","textData":{"emoji":{}},"text":"@yasserogier \n\nBasically what I need here is to create a pivot table of what was extracted so far this year in terms of volumes per month per type.\n\nSo if you can do it the same way you normally extract ad hoc data then I can make my own report. I just need the extracted date with the rest of the normal fields.\n\n@gillianoberholzer ","card":{"id":"5440b17399654d05f1a3c785","name":"CW - CCW245 - Experian extract","idShort":277,"shortLink":"Zie8ks2Z"},"board":{"id":"53d0c20db03b0a44cfcca509","name":"Cape Town - Kanban","shortLink":"0GuDZG62"},"list":{"id":"53d0c20db03b0a44cfcca50a","name":"All Tasks"}},"type":"commentCard","date":"2014-10-17T07:44:44.977Z","memberCreator":{"id":"53d2098c5dc4ef2c4b37773d","avatarHash":"cf33be632f5da9e22f4c332f7ece1542","fullName":"Neil Bosworth","initials":"NB","username":"neilbosworth"}}