{"id":"55b886996b2a40fe5789570b","idMemberCreator":"53cfbd67fd63aac7f152189c","data":{"listAfter":{"name":"In Testing (Max 10)","id":"53d0c20db03b0a44cfcca50d"},"listBefore":{"name":"In Progress (Max 9)","id":"548561eb7a11dac78511a729"},"board":{"shortLink":"nkiN4mz2","name":"Cape Town - 2015","id":"54855ffbe150073e233562be"},"card":{"shortLink":"abi1Kus3","idShort":488,"name":"CW - GCCW153 - I360 Verifiers error","id":"55b8765660d6ed4388b4f02d","idList":"53d0c20db03b0a44cfcca50d"},"old":{"idList":"548561eb7a11dac78511a729"}},"type":"updateCard","date":"2015-07-29T07:54:01.085Z","memberCreator":{"id":"53cfbd67fd63aac7f152189c","avatarHash":"c4073941033c6263ed206ed19771873b","fullName":"Stefan Bar","initials":"SB","username":"stefanbar"}}