{"id":"558cebe70464e77f1bc5b991","idMemberCreator":"53d2013aa69729f24a95888e","data":{"listAfter":{"name":"Opportunities In Testing (Max 10)","id":"53d0c20db03b0a44cfcca50d"},"listBefore":{"name":"In Progress (Max 9)","id":"548561eb7a11dac78511a729"},"board":{"shortLink":"nkiN4mz2","name":"Cape Town - 2015","id":"54855ffbe150073e233562be"},"card":{"shortLink":"JBj4wO0U","idShort":393,"name":"CW - CCWE35 - DAMOR capturing enhancement","id":"5587bb74eb4261ca2335da95","idList":"53d0c20db03b0a44cfcca50d"},"old":{"idList":"548561eb7a11dac78511a729"}},"type":"updateCard","date":"2015-06-26T06:06:31.087Z","memberCreator":{"id":"53d2013aa69729f24a95888e","avatarHash":null,"fullName":"Lungisa Ximbi","initials":"LX","username":"lungisaximbi"}}