{"id":"540555d4486a886377348cad","idMemberCreator":"53cfbb55f833a01546975bd3","data":{"listAfter":{"name":"Release Scheduled","id":"53f31658e909d9e4bbf56510"},"listBefore":{"name":"Ready To Release","id":"53d0c20db03b0a44cfcca50e"},"board":{"shortLink":"0GuDZG62","name":"Cape Town - Kanban","id":"53d0c20db03b0a44cfcca509"},"card":{"shortLink":"XSr3YO1C","idShort":120,"name":"CC - EH_5 (3) - Refine the process to add branch","id":"53edc5916691dc62522cd335","idList":"53f31658e909d9e4bbf56510"},"old":{"idList":"53d0c20db03b0a44cfcca50e"}},"type":"updateCard","date":"2014-09-02T05:29:56.039Z","memberCreator":{"id":"53cfbb55f833a01546975bd3","avatarHash":"f303f406818d7519d91c3c089e1c27a8","fullName":"Jako van Rensburg","initials":"JR","username":"jakovanrensburg"}}