{"id":"54f84308fc7a2792d07da5c5","checkItemStates":[],"closed":true,"dateLastActivity":"2015-04-08T06:00:46.856Z","desc":"I noticed in the TU file for the 3rd of March that the ID number of the following record has spaces in it. Please would you check and find out why it was extracted like this when we have validation in place to not let this happen?\n\nI|1|1|KNY|M|416|14|SER|20140402|3590.28|N|CJ BALLAN INCORPORATED|CJ BALLAN INC|044 3821173|DARWISH|ANGELIQUE|||||810521 0159 08 2||752 DAVIDSON STREET|HORNLEE|KNYSNA||KNYSNA|6570|J||||||||665575|N\n","descData":null,"idBoard":"5524c266ecb4ced4cdb44411","idList":"548561d74df012abdef092c7","idMembersVoted":[],"idShort":47,"idAttachmentCover":null,"manualCoverAttachment":false,"idLabels":["5524c403664ce8ff30010321"],"name":"CW - CCW296 - ID No validation","pos":2670591,"shortLink":"GxXRoQn8","badges":{"votes":0,"viewingMemberVoted":false,"subscribed":false,"fogbugz":"","checkItems":0,"checkItemsChecked":0,"comments":1,"attachments":0,"description":true,"due":null},"due":null,"email":"jakovanrensburg+53cfbb55f833a01546975bd3+54f84308fc7a2792d07da5c5+a8d6a0c18e61b8b4ba6f1c62666d2a81d46af247@boards.trello.com","idChecklists":[],"idMembers":[],"labels":[{"id":"5524c403664ce8ff30010321","idBoard":"5524c266ecb4ced4cdb44411","name":"Issue / Bug","color":"blue","uses":31}],"shortUrl":"https://trello.com/c/GxXRoQn8","subscribed":false,"url":"https://trello.com/c/GxXRoQn8/47-cw-ccw296-id-no-validation"}