{"id":"55ed2b034e9fe8dce97d3262","idMemberCreator":"53cfbb55f833a01546975bd3","data":{"listAfter":{"name":"In Testing (Max 10)","id":"53d0c20db03b0a44cfcca50d"},"listBefore":{"name":"Pending Tasks","id":"548561db38fd879b2bc329e5"},"board":{"shortLink":"nkiN4mz2","name":"Cape Town - 2015","id":"54855ffbe150073e233562be"},"card":{"shortLink":"9gxAGN67","idShort":571,"name":"SW - Company Watch to Alerts","id":"55ed29178777a8d2742c0db7","idList":"53d0c20db03b0a44cfcca50d"},"old":{"idList":"548561db38fd879b2bc329e5"}},"type":"updateCard","date":"2015-09-07T06:13:23.770Z","memberCreator":{"id":"53cfbb55f833a01546975bd3","avatarHash":"f303f406818d7519d91c3c089e1c27a8","fullName":"Jako van Rensburg","initials":"JR","username":"jakovanrensburg"}}