{"id":"540ef59c7ba786c615de05d1","checkItemStates":[],"closed":true,"dateLastActivity":"2014-09-26T06:43:59.729Z","desc":"In conjunction with the currently log being worked on by Lungisa for the bureau portal:\n\nPlease would you limit the number of queries that are displayed on screen and loaded in the background in all sections of the bureau portal as some sections are taking a long time to load and every time you swap tabs, it reloads all the queries again?","descData":{"emoji":{}},"idBoard":"53d0c20db03b0a44cfcca509","idList":"53d0c20db03b0a44cfcca50b","idMembersVoted":[],"idShort":185,"idAttachmentCover":null,"manualCoverAttachment":false,"idLabels":["5465641074d650d5671f958f"],"name":"CW - CCW229 - Bureau Portal change","pos":6619135,"shortLink":"Jje8rR8t","badges":{"votes":0,"viewingMemberVoted":false,"subscribed":false,"fogbugz":"","checkItems":0,"checkItemsChecked":0,"comments":6,"attachments":0,"description":true,"due":null},"due":null,"email":"jakovanrensburg+53cfbb55f833a01546975bd3+540ef59c7ba786c615de05d1+170d7aa9550a8f5f8cf5b1ed86f473203f1f0cbf@boards.trello.com","idChecklists":[],"idMembers":["53cfc3dbf80a9a2e4631c72c"],"labels":[{"id":"5465641074d650d5671f958f","idBoard":"53d0c20db03b0a44cfcca509","name":"Enhancement","color":"green","uses":99}],"shortUrl":"https://trello.com/c/Jje8rR8t","subscribed":false,"url":"https://trello.com/c/Jje8rR8t/185-cw-ccw229-bureau-portal-change"}