{"id":"53f3311ecb9542275b1be05c","idMemberCreator":"53cfbd67fd63aac7f152189c","data":{"board":{"shortLink":"0GuDZG62","name":"Cape Town - Kanban","id":"53d0c20db03b0a44cfcca509"},"card":{"shortLink":"Aqm13YJM","idShort":106,"name":"VW - Roles issue on UAT","id":"53eb1f27e7b4762ea403b60b"},"text":"@shaunviljoen  @gillianoberholzer please test on UAT."},"type":"commentCard","date":"2014-08-19T11:12:30.538Z","memberCreator":{"id":"53cfbd67fd63aac7f152189c","avatarHash":"c4073941033c6263ed206ed19771873b","fullName":"Stefan Bar","initials":"SB","username":"stefanbar"}}