{"id":"560b9d485c37b5229e20368c","idMemberCreator":"53d2098c5dc4ef2c4b37773d","data":{"dateLastEdited":"2015-09-30T08:29:31.569Z","textData":{"emoji":{}},"text":"@stefanbar \n\nYes please. But once again, we really need a solution for this. Either something to stop so many pages being sorted or a smart loading process to allow the user to continue. \n\nIt is entirely possible however that there is that many pages in a file.\n\nThanks.\n\n@gillianoberholzer @lylenutt @willemhuman ","card":{"id":"560b8ede1f0e264a191a284f","name":"CW - GCCW185 - System not assigning files","idShort":625,"shortLink":"D8hmJ3I7"},"board":{"id":"54855ffbe150073e233562be","name":"Cape Town - 2015","shortLink":"nkiN4mz2"},"list":{"id":"548561db38fd879b2bc329e5","name":"Pending Tasks"}},"type":"commentCard","date":"2015-09-30T08:28:56.731Z","memberCreator":{"id":"53d2098c5dc4ef2c4b37773d","avatarHash":"cf33be632f5da9e22f4c332f7ece1542","fullName":"Neil Bosworth","initials":"NB","username":"neilbosworth"}}