{"id":"53fec4d727a3559a4b96b5af","checkItemStates":[],"closed":true,"dateLastActivity":"2014-09-25T17:21:05.991Z","desc":"After a Debt Review Order or Application is captured and the case arrives on the verifier’s screen, the DOB defaults to 2014 or a date in the 1900s and not what the capturer inputted.\n\nID numbers of recently captured cases as per Cobus’ request are:\n\n7002070404081\n6707250346081\n\nThey are currently awaiting verification at the time of writing this.\n","descData":{"emoji":{}},"idBoard":"53d0c20db03b0a44cfcca509","idList":"53f31658e909d9e4bbf56510","idMembersVoted":[],"idShort":145,"idAttachmentCover":null,"manualCoverAttachment":false,"idLabels":["5465641074d650d5671f9594"],"name":"CW - CCW226 - DR Order and App DOB issue","pos":7372799,"shortLink":"BVW4gseZ","badges":{"votes":0,"viewingMemberVoted":false,"subscribed":false,"fogbugz":"","checkItems":0,"checkItemsChecked":0,"comments":7,"attachments":1,"description":true,"due":"2014-09-25T16:30:00.000Z"},"due":"2014-09-25T16:30:00.000Z","email":"jakovanrensburg+53cfbb55f833a01546975bd3+53fec4d727a3559a4b96b5af+c6222634a22bd9b0f52216b77ca0f8856079b518@boards.trello.com","idChecklists":[],"idMembers":[],"labels":[{"id":"5465641074d650d5671f9594","idBoard":"53d0c20db03b0a44cfcca509","name":"Issue / Bug","color":"blue","uses":78}],"shortUrl":"https://trello.com/c/BVW4gseZ","subscribed":false,"url":"https://trello.com/c/BVW4gseZ/145-cw-ccw226-dr-order-and-app-dob-issue"}