{"id":"558bdd7fcc1448665478a55c","idMemberCreator":"53cfbb55f833a01546975bd3","data":{"list":{"name":"Release Scheduled","id":"548561f8c11ae3f322997bb4"},"board":{"shortLink":"nkiN4mz2","name":"Cape Town - 2015","id":"54855ffbe150073e233562be"},"card":{"shortLink":"UO3RzeEv","idShort":2,"name":"Android - SW - Phase 2","id":"53e328229871f8d5a9feb82f"},"text":"@nicolastyler we can create a new card when you get time for this again. We now wait for the App of the Year"},"type":"commentCard","date":"2015-06-25T10:52:47.742Z","memberCreator":{"id":"53cfbb55f833a01546975bd3","avatarHash":"f303f406818d7519d91c3c089e1c27a8","fullName":"Jako van Rensburg","initials":"JR","username":"jakovanrensburg"}}