{"id":"5552e8061bc9662d42fd91d1","idMemberCreator":"53d0b2dfdbb677b722c39443","data":{"listAfter":{"name":"In Progress (Max 9)","id":"548561eb7a11dac78511a729"},"listBefore":{"name":"Pending Tasks","id":"548561db38fd879b2bc329e5"},"board":{"shortLink":"nkiN4mz2","name":"Cape Town - 2015","id":"54855ffbe150073e233562be"},"card":{"shortLink":"uB5l7x2G","idShort":322,"name":"SW - SG Diagram","id":"555065d8edf6fe42068937b3","idList":"548561eb7a11dac78511a729"},"old":{"idList":"548561db38fd879b2bc329e5"}},"type":"updateCard","date":"2015-05-13T05:58:30.040Z","memberCreator":{"id":"53d0b2dfdbb677b722c39443","avatarHash":null,"fullName":"Willem Human","initials":"WH","username":"willemhuman"}}