{"id":"5552f38650498b4eba229602","idMemberCreator":"53cfbb55f833a01546975bd3","data":{"list":{"name":"In Testing (Max 10)","id":"53d0c20db03b0a44cfcca50d"},"board":{"shortLink":"nkiN4mz2","name":"Cape Town - 2015","id":"54855ffbe150073e233562be"},"card":{"shortLink":"mF0e4xEF","idShort":215,"name":"VW - Unable to buy credits on Vaultworks","id":"54eacd3bb9f2cad22423d2c1"},"text":"@gillianoberholzer @shaunviljoen Is this working now?"},"type":"commentCard","date":"2015-05-13T06:47:34.099Z","memberCreator":{"id":"53cfbb55f833a01546975bd3","avatarHash":"f303f406818d7519d91c3c089e1c27a8","fullName":"Jako van Rensburg","initials":"JR","username":"jakovanrensburg"}}