{"id":"541154c2364d9176765498d2","idMemberCreator":"53d097f91cb25024461e3efd","data":{"list":{"name":"Gathering Information","id":"53db2201d11c89ed43fc5a6a"},"board":{"shortLink":"0GuDZG62","name":"Cape Town - Kanban","id":"53d0c20db03b0a44cfcca509"},"card":{"shortLink":"Lo7yRaB3","idShort":148,"name":"CW - CCW228 - DR Orders to TU","id":"53feed572daaa1d044ecffe3"},"text":"Task not complete as yet @jakovanrensburg"},"type":"commentCard","date":"2014-09-11T07:52:34.209Z","memberCreator":{"id":"53d097f91cb25024461e3efd","avatarHash":null,"fullName":"Gillian Oberholzer","initials":"GO","username":"gillianoberholzer"}}