{"id":"54e739bc3568baac7d023708","idMemberCreator":"53d2098c5dc4ef2c4b37773d","data":{"list":{"name":"Pending Tasks","id":"548561db38fd879b2bc329e5"},"board":{"shortLink":"nkiN4mz2","name":"Cape Town - 2015","id":"54855ffbe150073e233562be"},"card":{"shortLink":"fHQce9AT","idShort":213,"name":"CW - GCCW110 - Upload images issue","id":"54e716a2c6b449f424dd67a9"},"text":"@gillianoberholzer is someone looking at this? It is marked urgent but we haven\u0027t had any feedback"},"type":"commentCard","date":"2015-02-20T13:42:20.849Z","memberCreator":{"id":"53d2098c5dc4ef2c4b37773d","avatarHash":"cf33be632f5da9e22f4c332f7ece1542","fullName":"Neil Bosworth","initials":"NB","username":"neilbosworth"}}