{"id":"53f5f1764678faa90a7aa3f1","idMemberCreator":"53cfc3dbf80a9a2e4631c72c","data":{"board":{"shortLink":"0GuDZG62","name":"Cape Town - Kanban","id":"53d0c20db03b0a44cfcca509"},"card":{"shortLink":"lLP50VhB","idShort":132,"name":"CW - CCW221 - AgentUpliftedTotal and AgentOnHoldTotal reports issue","id":"53f589aa90e87503e6a09f93"},"text":"Hi @gillianoberholzer \n\nThis is a change that Willem will change.\nWillem - just call the correct sproc for each report. basically swop the reports for the above mentioned reports\n\n@willemhuman"},"type":"commentCard","date":"2014-08-21T13:17:42.849Z","memberCreator":{"id":"53cfc3dbf80a9a2e4631c72c","avatarHash":null,"fullName":"Yasser Ogier","initials":"YO","username":"yasserogier"}}