{"id":"5524c65e2009a80214997177","idMemberCreator":"53cfbb55f833a01546975bd3","data":{"listAfter":{"name":"CourtWorks","id":"5524c64e54a761ddb4f0208e"},"listBefore":{"name":"Support Investigation","id":"548561d74df012abdef092c7"},"board":{"shortLink":"Q7flSzKF","name":"Investigation","id":"5524c266ecb4ced4cdb44411"},"card":{"shortLink":"udY4ZTBU","idShort":9,"name":"CW - CCW237 - No extracting judgments with passport numbers","id":"5423cfc7fa26a2bc27eb6f94","idList":"5524c64e54a761ddb4f0208e"},"old":{"idList":"548561d74df012abdef092c7"}},"type":"updateCard","date":"2015-04-08T06:10:38.217Z","memberCreator":{"id":"53cfbb55f833a01546975bd3","avatarHash":"f303f406818d7519d91c3c089e1c27a8","fullName":"Jako van Rensburg","initials":"JR","username":"jakovanrensburg"}}