{"id":"560143408f86ecd3751818c1","idMemberCreator":"53d0b2dfdbb677b722c39443","data":{"listAfter":{"name":"In Progress (Max 9)","id":"548561eb7a11dac78511a729"},"listBefore":{"name":"Pending Tasks","id":"548561db38fd879b2bc329e5"},"board":{"shortLink":"nkiN4mz2","name":"Cape Town - 2015","id":"54855ffbe150073e233562be"},"card":{"shortLink":"fkmeut6z","idShort":607,"name":"SW - SG issue","id":"5601362908774b0276b72b98","idList":"548561eb7a11dac78511a729"},"old":{"idList":"548561db38fd879b2bc329e5"}},"type":"updateCard","date":"2015-09-22T12:02:08.549Z","memberCreator":{"id":"53d0b2dfdbb677b722c39443","avatarHash":null,"fullName":"Willem Human","initials":"WH","username":"willemhuman"}}