{"id":"55a5ffad6b1dcf4f3b6bc621","idMemberCreator":"53cfbbfb4c2831b3f1b4bffb","data":{"list":{"name":"CW - Awaiting Feedback","id":"5524c64e54a761ddb4f0208e"},"board":{"name":"Cape Town - 2015","id":"54855ffbe150073e233562be"},"card":{"shortLink":"6UoMvSJl","idShort":71,"name":"CW / CC - Image Viewer Limitations Per Client","id":"53d209056831268469db5499"},"text":"@gillianoberholzer I dont need it anymore thank you, not sure about the Dev guys."},"type":"commentCard","date":"2015-07-15T06:37:33.629Z","memberCreator":{"id":"53cfbbfb4c2831b3f1b4bffb","avatarHash":"ec2557f35d26598c8a21e2802c04f5c6","fullName":"Cobus Pienaar","initials":"CP","username":"cobuspienaar"}}