{"id":"53fc40121c615cd23fc1a29a","idMemberCreator":"53cfc3dbf80a9a2e4631c72c","data":{"board":{"shortLink":"0GuDZG62","name":"Cape Town - Kanban","id":"53d0c20db03b0a44cfcca509"},"card":{"shortLink":"DEFWCQVG","idShort":141,"name":"CW - GCCW059 - Confirm if matter sent through to TU and provide CaseID","id":"53f72962abfc360a181263b3"},"text":"Hi @gillianoberholzer \n\nthis record was extracted to TU on \"2013-11-25 00:39:19.447\"\nID - 133188"},"type":"commentCard","date":"2014-08-26T08:06:42.638Z","memberCreator":{"id":"53cfc3dbf80a9a2e4631c72c","avatarHash":null,"fullName":"Yasser Ogier","initials":"YO","username":"yasserogier"}}