{"id":"56091d72a62efa9b98beb6ba","idMemberCreator":"53d0b2dfdbb677b722c39443","data":{"listAfter":{"name":"In Testing (Max 10)","id":"53d0c20db03b0a44cfcca50d"},"listBefore":{"name":"In Progress (Max 9)","id":"548561eb7a11dac78511a729"},"board":{"shortLink":"nkiN4mz2","name":"Cape Town - 2015","id":"54855ffbe150073e233562be"},"card":{"shortLink":"xivhOFzX","idShort":582,"name":"SW - CIPC director issue","id":"55eeb9d4c3180bc03d041b10","idList":"53d0c20db03b0a44cfcca50d"},"old":{"idList":"548561eb7a11dac78511a729"}},"type":"updateCard","date":"2015-09-28T10:58:58.955Z","memberCreator":{"id":"53d0b2dfdbb677b722c39443","avatarHash":null,"fullName":"Willem Human","initials":"WH","username":"willemhuman"}}