{"id":"55b9f5e855d08ad2222a9cd5","idMemberCreator":"53d097f91cb25024461e3efd","data":{"list":{"name":"Pending Tasks","id":"548561db38fd879b2bc329e5"},"board":{"shortLink":"nkiN4mz2","name":"Cape Town - 2015","id":"54855ffbe150073e233562be"},"card":{"shortLink":"fFcTJbt4","idShort":498,"name":"SW - SG list issue","id":"55b9f5c7496d69a21cc37d99"},"text":"@willemhuman Nog een"},"type":"commentCard","date":"2015-07-30T10:01:12.621Z","memberCreator":{"id":"53d097f91cb25024461e3efd","avatarHash":null,"fullName":"Gillian Oberholzer","initials":"GO","username":"gillianoberholzer"}}