{"id":"54105ce57afb9c69247ae0ce","idMemberCreator":"53cfc3dbf80a9a2e4631c72c","data":{"list":{"name":"In Progress (Max 9)","id":"53d0c20db03b0a44cfcca50b"},"board":{"shortLink":"0GuDZG62","name":"Cape Town - Kanban","id":"53d0c20db03b0a44cfcca509"},"card":{"shortLink":"MtW4m3tB","idShort":193,"name":"SW - Bridging - Reassign","id":"5410573cc3096caa7e1eeeba"},"text":"HI @gillianoberholzer  @shaunviljoen \n\nI have reassigned the Application.\nPlease test and confirm."},"type":"commentCard","date":"2014-09-10T14:15:01.970Z","memberCreator":{"id":"53cfc3dbf80a9a2e4631c72c","avatarHash":null,"fullName":"Yasser Ogier","initials":"YO","username":"yasserogier"}}