{"id":"555b1b014dcec69dc5981f0e","idMemberCreator":"53d097f91cb25024461e3efd","data":{"list":{"name":"CourtWorks (Analysis)","id":"5524c64e54a761ddb4f0208e"},"board":{"name":"Investigation","id":"5524c266ecb4ced4cdb44411"},"card":{"shortLink":"CEbk26IR","idShort":97,"name":"CW - Rescission not sent to bureaus","id":"5555bb0f3ddc6a186eeca0ab"},"text":"@yasserogier Neil added the id number and advised that the case he amended is from the Courts. The attorney has also added the case so the attorney case will need to be disabled please."},"type":"commentCard","date":"2015-05-19T11:14:09.747Z","memberCreator":{"id":"53d097f91cb25024461e3efd","avatarHash":null,"fullName":"Gillian Oberholzer","initials":"GO","username":"gillianoberholzer"}}