{"id":"55ed6e9a5f3bb716e93d9ae8","idMemberCreator":"53cfbd67fd63aac7f152189c","data":{"list":{"name":"Pending Tasks","id":"548561db38fd879b2bc329e5"},"board":{"shortLink":"nkiN4mz2","name":"Cape Town - 2015","id":"54855ffbe150073e233562be"},"card":{"shortLink":"WVDMoId7","idShort":574,"name":"CW - CCW375 - Auto sorter issue","id":"55ed6b8d32f300c81d8cf5c9"},"text":"Is this still occurring? As i checked the front end server and there\u0027s still space available. @gillianoberholzer @cobuspienaar (See attachment)"},"type":"commentCard","date":"2015-09-07T11:01:46.930Z","memberCreator":{"id":"53cfbd67fd63aac7f152189c","avatarHash":"c4073941033c6263ed206ed19771873b","fullName":"Stefan Bar","initials":"SB","username":"stefanbar"}}