{"id":"557932ae18ebc05cd44f1d08","idMemberCreator":"53cfc3dbf80a9a2e4631c72c","data":{"dateLastEdited":"2015-06-11T07:09:31.477Z","text":"@shaunviljoen @neilbosworth @gillianoberholzer \n\nWhen you say \"Our Records\", are you referring to the actual record to changed on Attorney CW or the Data That went out to the Bureau?\n\nNeil cannot change Attorney CW records. Only Capturing side. If the case is a Capturing CW record then i will provide the Case ID for Neil to ammend.\n","card":{"id":"55792b3e6141dc36ed797a66","name":"CW - Attorney side: Update of Attorney Info","idShort":370,"shortLink":"RVLYMRux"},"board":{"name":"Cape Town - 2015","id":"54855ffbe150073e233562be"},"list":{"id":"548561db38fd879b2bc329e5","name":"Pending Tasks"}},"type":"commentCard","date":"2015-06-11T07:03:10.551Z","memberCreator":{"id":"53cfc3dbf80a9a2e4631c72c","avatarHash":null,"fullName":"Yasser Ogier","initials":"YO","username":"yasserogier"}}