{"id":"53e8af34d6d395de09120599","checkItemStates":[],"closed":true,"dateLastActivity":"2014-12-08T08:35:17.810Z","desc":"Please would you make some images available via the UAT web service so that Inoxico can test.","descData":{"emoji":{}},"idBoard":"53d0c20db03b0a44cfcca509","idList":"53f31658e909d9e4bbf56510","idMembersVoted":[],"idShort":98,"idAttachmentCover":null,"manualCoverAttachment":false,"idLabels":["5465641074d650d5671f9590"],"name":"CW - Images","pos":180223.65625,"shortLink":"k1m82q1K","badges":{"votes":0,"viewingMemberVoted":false,"subscribed":false,"fogbugz":"","checkItems":0,"checkItemsChecked":0,"comments":10,"attachments":1,"description":true,"due":"2014-08-27T15:00:00.000Z"},"due":"2014-08-27T15:00:00.000Z","email":"jakovanrensburg+53cfbb55f833a01546975bd3+53e8af34d6d395de09120599+1b6d5a4c06677ab365cdacc47c4a40551dd45e4b@boards.trello.com","idChecklists":[],"idMembers":["53d097f91cb25024461e3efd"],"labels":[{"id":"5465641074d650d5671f9590","idBoard":"53d0c20db03b0a44cfcca509","name":"Single Task / Report","color":"yellow","uses":73}],"shortUrl":"https://trello.com/c/k1m82q1K","subscribed":false,"url":"https://trello.com/c/k1m82q1K/98-cw-images"}