{"id":"53d5fefc23a65094efeea2a8","idMemberCreator":"53cfbb55f833a01546975bd3","data":{"board":{"name":"Cape Town - 2015","id":"54855ffbe150073e233562be"},"card":{"shortLink":"DsY5HbnZ","idShort":56,"name":"VW - API Documentation","id":"53d229736fa7ae478db2c823"},"text":"@lungisaximbi due date?"},"type":"commentCard","date":"2014-07-28T07:42:52.312Z","memberCreator":{"id":"53cfbb55f833a01546975bd3","avatarHash":"f303f406818d7519d91c3c089e1c27a8","fullName":"Jako van Rensburg","initials":"JR","username":"jakovanrensburg"}}