{"id":"54192deb1b1984b0a16f91cc","idMemberCreator":"53cfbb55f833a01546975bd3","data":{"listAfter":{"name":"Release Scheduled","id":"53f31658e909d9e4bbf56510"},"listBefore":{"name":"Ready To Release","id":"53d0c20db03b0a44cfcca50e"},"board":{"shortLink":"0GuDZG62","name":"Cape Town - Kanban","id":"53d0c20db03b0a44cfcca509"},"card":{"shortLink":"Rw9NPoZQ","idShort":26,"name":"CW - New Document Type: Rehabilitation","id":"53d20da62ba7690e1d84255c","idList":"53f31658e909d9e4bbf56510"},"old":{"idList":"53d0c20db03b0a44cfcca50e"}},"type":"updateCard","date":"2014-09-17T06:44:59.361Z","memberCreator":{"id":"53cfbb55f833a01546975bd3","avatarHash":"f303f406818d7519d91c3c089e1c27a8","fullName":"Jako van Rensburg","initials":"JR","username":"jakovanrensburg"}}