{"id":"55093a9d3ef50375ddde3c9a","idMemberCreator":"53cfbd67fd63aac7f152189c","data":{"list":{"name":"Ready To Release","id":"53d0c20db03b0a44cfcca50e"},"board":{"shortLink":"nkiN4mz2","name":"Cape Town - 2015","id":"54855ffbe150073e233562be"},"card":{"shortLink":"kdBlh1em","idShort":225,"name":"CW- CCW293 - e4 logo judgment","id":"54ef1e086f65eba980b338a3"},"text":"@gillianoberholzer @cobuspienaar Please sign this card off before moving it to the \"Ready To Release\" column. Otherwise we have no prove."},"type":"commentCard","date":"2015-03-18T08:43:09.711Z","memberCreator":{"id":"53cfbd67fd63aac7f152189c","avatarHash":"c4073941033c6263ed206ed19771873b","fullName":"Stefan Bar","initials":"SB","username":"stefanbar"}}