{"id":"5459e64e80346103c3adc4d6","idMemberCreator":"53cfc3dbf80a9a2e4631c72c","data":{"list":{"name":"Awaiting Support / More Info","id":"53db2201d11c89ed43fc5a6a"},"board":{"shortLink":"0GuDZG62","name":"Cape Town - Kanban","id":"53d0c20db03b0a44cfcca509"},"card":{"shortLink":"BF3fnX0g","idShort":321,"name":"Report Central - Users By Company","id":"545879dd35a20caa9bbc3dca"},"text":"@gillianoberholzer \n\nthere nothing further that i can do on this issue.\nThe reports display correctly for you and dev. i am not sure what the problem is with Shaun\u0027s laptop.\n\nyou can archive if you want."},"type":"commentCard","date":"2014-11-05T08:56:46.516Z","memberCreator":{"id":"53cfc3dbf80a9a2e4631c72c","avatarHash":null,"fullName":"Yasser Ogier","initials":"YO","username":"yasserogier"}}