{"id":"54b3998ea0b26a761cc1b93f","idMemberCreator":"53cfbd67fd63aac7f152189c","data":{"listAfter":{"name":"In Progress (Max 9)","id":"548561eb7a11dac78511a729"},"listBefore":{"name":"Pending Tasks","id":"548561db38fd879b2bc329e5"},"board":{"shortLink":"nkiN4mz2","name":"Cape Town - 2015","id":"54855ffbe150073e233562be"},"card":{"shortLink":"JhyVgvql","idShort":121,"name":"CC - Diane STBB CC issue","id":"54b390c134ec76eab638ba43","idList":"548561eb7a11dac78511a729"},"old":{"idList":"548561db38fd879b2bc329e5"}},"type":"updateCard","date":"2015-01-12T09:53:18.461Z","memberCreator":{"id":"53cfbd67fd63aac7f152189c","avatarHash":"c4073941033c6263ed206ed19771873b","fullName":"Stefan Bar","initials":"SB","username":"stefanbar"}}