{"id":"55d5a0a369358aedf03dbbde","idMemberCreator":"53cfc3dbf80a9a2e4631c72c","data":{"dateLastEdited":"2015-08-20T09:53:14.586Z","text":"@neilbosworth @gillianoberholzer\n\nAgreed... BUT.... there is always a \"BUT\" :smile: \n\nWe have 8 million ID\u0027s and they dont.\n\n1. Cant Inoxico provide us with their ID\u0027s so that we can give them a linked CaseInformationID. Should be way less than 8 million records they will provide.\n\n2. We create a method for them that works on the OLD ID and we dont bill them for the calls.\n\n\nPS:- Addworks did call earlier.\n\n@gillianoberholzer @cobuspienaar @stefanbar @jakovanrensburg @willemhuman","card":{"id":"55d580717c9d7d0f04f3ac97","name":"CW - CCW363 - Inoxico Incorrect images via API","idShort":529,"shortLink":"tZOIs1AN"},"board":{"name":"Opportunities \u0026 Feedback - 2015","id":"5524c266ecb4ced4cdb44411"},"list":{"id":"548561eb7a11dac78511a729","name":"In Progress (Max 9)"}},"type":"commentCard","date":"2015-08-20T09:40:51.125Z","memberCreator":{"id":"53cfc3dbf80a9a2e4631c72c","avatarHash":null,"fullName":"Yasser Ogier","initials":"YO","username":"yasserogier"}}