{"id":"552d04ab29ee90e7f614c127","idMemberCreator":"53d0b2dfdbb677b722c39443","data":{"list":{"name":"In Progress (Max 9)","id":"548561eb7a11dac78511a729"},"board":{"name":"Investigation","id":"5524c266ecb4ced4cdb44411"},"card":{"shortLink":"hLh78Cq8","idShort":296,"name":"SW - SG link to retrieve docs - URGENT","id":"552bc1c107e37a1eddf94e88"},"text":"@shaunviljoen @gillianoberholzer @jakovanrensburg @cobuspienaar\nI will be able to do this.\nI am creating a app now to provide the necessary details from a LPI code to  request SG Diagram."},"type":"commentCard","date":"2015-04-14T12:14:35.114Z","memberCreator":{"id":"53d0b2dfdbb677b722c39443","avatarHash":null,"fullName":"Willem Human","initials":"WH","username":"willemhuman"}}