{"id":"54e7847b9bdbd9c6d9d3df3d","idMemberCreator":"53cfbbfb4c2831b3f1b4bffb","data":{"list":{"name":"Pending Tasks","id":"548561db38fd879b2bc329e5"},"board":{"shortLink":"nkiN4mz2","name":"Cape Town - 2015","id":"54855ffbe150073e233562be"},"card":{"shortLink":"fHQce9AT","idShort":213,"name":"CW - GCCW110 - Upload images issue","id":"54e716a2c6b449f424dd67a9"},"text":"@stefanbar @willemhuman @gillianoberholzer @neilbosworth This was already resolved just after 1 this afternoon. Willem restarted the App pool on Courtworks."},"type":"commentCard","date":"2015-02-20T19:01:15.934Z","memberCreator":{"id":"53cfbbfb4c2831b3f1b4bffb","avatarHash":"ec2557f35d26598c8a21e2802c04f5c6","fullName":"Cobus Pienaar","initials":"CP","username":"cobuspienaar"}}