{"id":"53fc8cd1f131feeb546deacb","idMemberCreator":"53cfbd67fd63aac7f152189c","data":{"board":{"shortLink":"0GuDZG62","name":"Cape Town - Kanban","id":"53d0c20db03b0a44cfcca509"},"card":{"shortLink":"jClsY22p","idShort":109,"name":"VW - Safety Zone duplicated","id":"53eb4f165cfaf1d0fd19f21f"},"text":"@jakovanrensburg @gillianoberholzer I\u0027ve tried numerous ways to replicating this issue/bug and cannot re-create it, perhaps the duplication and other fixes that @lylenutt did sorted it out. Please test."},"type":"commentCard","date":"2014-08-26T13:34:09.797Z","memberCreator":{"id":"53cfbd67fd63aac7f152189c","avatarHash":"c4073941033c6263ed206ed19771873b","fullName":"Stefan Bar","initials":"SB","username":"stefanbar"}}