{"id":"55421cb43401a12a98f957f1","idMemberCreator":"53d097f91cb25024461e3efd","data":{"list":{"name":"SearchWorks (Analysis)","id":"5524c64b943ab911fd342f63"},"board":{"shortLink":"Q7flSzKF","name":"Investigation","id":"5524c266ecb4ced4cdb44411"},"card":{"shortLink":"OcZQy7pr","idShort":86,"name":"SW - v1 login issue","id":"5541fcf5bf9164597dcc9ec3"},"text":"@yasserogier They need to delist a default. The have tried resetting the password a few times. We need to log in to check quick. \n\nYour questions answered:\n\nDid you try to unlock the user already? Yes\nPlease also confirm if this is a Legal Suite issue? Not as far as we are aware. Query is regarding defaults which is not part of the legal suite integration.\nIs the user still supposed to be active on V1? No, as mentioned this is just to check on a historical default in order to delist. Client is active on V2."},"type":"commentCard","date":"2015-04-30T12:14:44.855Z","memberCreator":{"id":"53d097f91cb25024461e3efd","avatarHash":null,"fullName":"Gillian Oberholzer","initials":"GO","username":"gillianoberholzer"}}