{"id":"5458ece5cbf781f23f987dd5","idMemberCreator":"53cfc3dbf80a9a2e4631c72c","data":{"list":{"name":"All Tasks","id":"53d0c20db03b0a44cfcca50a"},"board":{"shortLink":"0GuDZG62","name":"Cape Town - Kanban","id":"53d0c20db03b0a44cfcca509"},"card":{"shortLink":"bSHkgpFi","idShort":323,"name":"CW - Client unable to load Rescission","id":"5458da9e9b347cfbd236b27b"},"text":"@gillianoberholzer \n\nI have sent an email to Neil including you, asking wether we should change the validation of inserting a new case with a different Doc Type. \n\nWaiting on Neil\u0027s response.\nThe request i made should be done."},"type":"commentCard","date":"2014-11-04T15:12:37.983Z","memberCreator":{"id":"53cfc3dbf80a9a2e4631c72c","avatarHash":null,"fullName":"Yasser Ogier","initials":"YO","username":"yasserogier"}}