{"id":"53e23063fcad9305518aa8cc","idMemberCreator":"53d0b2dfdbb677b722c39443","data":{"board":{"shortLink":"0GuDZG62","name":"Cape Town - Kanban","id":"53d0c20db03b0a44cfcca509"},"card":{"shortLink":"52vEOSQK","idShort":73,"name":"CC - Update the UI","id":"53db979398b68295c55b55da"},"text":"@gillianoberholzer @jakovanrensburg @shaunviljoen \nHi - made the suggested changes, please go check it out..."},"type":"commentCard","date":"2014-08-06T13:40:51.564Z","memberCreator":{"id":"53d0b2dfdbb677b722c39443","avatarHash":null,"fullName":"Willem Human","initials":"WH","username":"willemhuman"}}